mkdocs_auto_tag_plugin/__init__.py
mkdocs_auto_tag_plugin/plugin.py
mkdocs_auto_tag_plugin/utils.py
mkdocs_auto_tag_plugin-0.1.3.dist-info/LICENSE
mkdocs_auto_tag_plugin-0.1.3.dist-info/METADATA
mkdocs_auto_tag_plugin-0.1.3.dist-info/WHEEL
mkdocs_auto_tag_plugin-0.1.3.dist-info/entry_points.txt
mkdocs_auto_tag_plugin-0.1.3.dist-info/top_level.txt
mkdocs_auto_tag_plugin-0.1.3.dist-info/RECORD
