Metadata-Version: 2.1
Name: mkdocs-auto-tag-plugin
Version: 0.1.3
Summary: Add tags to your MkDocs pages based on their path / file name
Home-page: https://github.com/six-two/mkdocs-auto-tag-plugin
Author: six-two
Author-email: pip@six-two.dev
License: MIT License
Classifier: License :: OSI Approved :: MIT License
Classifier: Operating System :: POSIX :: Linux
Classifier: Programming Language :: Python :: 3
Classifier: Programming Language :: Python :: 3.9
Classifier: Programming Language :: Python :: 3.10
Requires-Python: >=3.9
License-File: LICENSE
Requires-Dist: mkdocs (>=1.4.0)
